pyobs_asi/__init__.py
pyobs_asi/asicamera.py
pyobs_asi-1.1.0.dist-info/METADATA
pyobs_asi-1.1.0.dist-info/WHEEL
pyobs_asi-1.1.0.dist-info/licenses/LICENSE
pyobs_asi-1.1.0.dist-info/RECORD
