Metadata-Version: 2.4
Name: pyobs-asi
Version: 1.1.0
Summary: pyobs model for ASI cameras
Author-email: Tim-Oliver Husser <thusser@uni-goettingen.de>
License-Expression: MIT
License-File: LICENSE
Requires-Python: >=3.11
Requires-Dist: numpy<3,>=2.2.5
Requires-Dist: pyobs-core<2,>=1
Requires-Dist: zwoasi>=0.2.0
